<?xml version="1.0" encoding="utf-8"?>
<SoundBanksInfo Platform="Windows" BasePlatform="Windows" SchemaVersion="16" SoundBankVersion="145">
	<RootPaths>
		<ProjectRoot>../..</ProjectRoot>
		<SourceFilesRoot>../../.cache/Windows</SourceFilesRoot>
		<SoundBanksRoot>.</SoundBanksRoot>
		<ExternalSourcesInputFile></ExternalSourcesInputFile>
		<ExternalSourcesOutputRoot>.</ExternalSourcesOutputRoot>
	</RootPaths>
	<DialogueEvents/>
	<SoundBanks>
		<SoundBank Id="1355168291" Type="User" Language="SFX" Hash="{73D02698-6C8F-8457-9A36-F1C960C7F721}">
			<ShortName>Init</ShortName>
			<Path>Init.bnk</Path>
			<Plugins>
				<AudioDevices>
					<Plugin Id="2317455096" Name="No_Output" LibName="No Output" LibId="11862023"/>
					<Plugin Id="3859886410" Name="System" LibName="System" LibId="11403271"/>
				</AudioDevices>
			</Plugins>
			<Busses>
				<Bus Id="1697111475" Name="BGM Bus"/>
				<Bus Id="3803692087" Name="Master Audio Bus"/>
			</Busses>
		</SoundBank>
		<SoundBank Id="2228651116" Type="User" Language="SFX" Hash="{08E7BE16-29E0-16A4-B241-0291537E8AA6}">
			<ShortName>Main_SoundBank</ShortName>
			<Path>Main_SoundBank.bnk</Path>
			<Media>
				<File Id="876023904" Language="SFX" Streaming="false" Location="Memory">
					<ShortName>041923 bulletsketch 155.wav</ShortName>
					<CachePath>SFX/041923 bulletsketch 155_D79FB2B7.wem</CachePath>
				</File>
			</Media>
			<Events>
				<Event Id="486851409" Name="Play_BGM_Playlist_1" DurationType="Infinite">
					<MediaRefs>
						<MediaRef Id="876023904"/>
					</MediaRefs>
				</Event>
			</Events>
		</SoundBank>
	</SoundBanks>
	<FileHash>{656F748E-3A1F-F79E-F647-AAF48F1ED098}</FileHash>
</SoundBanksInfo>
